README.md
setup.py
hostage/__init__.py
hostage/core.py
hostage/evaluator.py
hostage.egg-info/PKG-INFO
hostage.egg-info/SOURCES.txt
hostage.egg-info/dependency_links.txt
hostage.egg-info/requires.txt
hostage.egg-info/top_level.txt
hostage/evaluators/__init__.py
hostage/evaluators/base.py
hostage/evaluators/editor.py
hostage/evaluators/git.py
hostage/evaluators/github.py
hostage/evaluators/gradle.py
hostage/evaluators/http.py
hostage/evaluators/playstore.py
hostage/evaluators/slack.py
hostage/handlers/__init__.py
hostage/handlers/base.py