Metadata-Version: 1.1
Name: hostage
Version: 0.8.0
Summary: You'll WANT to release it
Home-page: https://github.com/dhleong/hostage
Author: Daniel Leong
Author-email: me@dhleong.net
License: UNKNOWN
Download-URL: https://github.com/dhleong/hostage/tarball/0.8.0
Keywords: release,script
Platform: UNKNOWN
